plover_vim/__init__.py
plover_vim/Emily_modifier/__init__.py
plover_vim/Emily_modifier/builtins.py
plover_vim/Emily_modifier/config.py
plover_vim/Emily_modifier/defaults.py
plover_vim/Emily_modifier/test.py
plover_vim/Emily_modifier/util.py
plover_vim/Josiah_modifier/__init__.py
plover_vim/Josiah_modifier/builtins.py
plover_vim/Josiah_modifier/config.py
plover_vim/Josiah_modifier/defaults.py
plover_vim/Josiah_modifier/test.py
plover_vim/Josiah_modifier/util.py
plover_vim/command_letter/__init__.py
plover_vim/command_letter/builtins.py
plover_vim/command_letter/config.py
plover_vim/command_letter/defaults.py
plover_vim/command_letter/test.py
plover_vim/command_letter/util.py
plover_vim/command_letter_2/__init__.py
plover_vim/command_letter_2/builtins.py
plover_vim/command_letter_2/config.py
plover_vim/command_letter_2/defaults.py
plover_vim/command_letter_2/test.py
plover_vim/command_letter_2/util.py
plover_vim/command_object/__init__.py
plover_vim/command_object/builtins.py
plover_vim/command_object/config.py
plover_vim/command_object/defaults.py
plover_vim/command_object/test.py
plover_vim/command_object/util.py
plover_vim/easy_motion/__init__.py
plover_vim/easy_motion/builtins.py
plover_vim/easy_motion/config.py
plover_vim/easy_motion/defaults.py
plover_vim/easy_motion/test.py
plover_vim/easy_motion/util.py
plover_vim/relative_number/Roman_numeral.py
plover_vim/relative_number/__init__.py
plover_vim/relative_number/builtins.py
plover_vim/relative_number/config.py
plover_vim/relative_number/defaults.py
plover_vim/relative_number/test.py
plover_vim/relative_number/util.py
plover_vim/shared/__init__.py
plover_vim/shared/builtins.py
plover_vim/shared/test.py
plover_vim/shared/util.py
plover_vim-0.13.0.dist-info/LICENSE
plover_vim-0.13.0.dist-info/METADATA
plover_vim-0.13.0.dist-info/WHEEL
plover_vim-0.13.0.dist-info/top_level.txt
plover_vim-0.13.0.dist-info/zip-safe
plover_vim-0.13.0.dist-info/RECORD
