Metadata-Version: 2.1
Name: plover_vim
Version: 0.13.0
Summary: (mostly) single stroke vim commands
Home-page: https://github.com/Josiah-tan/plover-vim
Author: Josiah Tan
License: GNU General Public License v3 (GPLv3)
Keywords: plover plover_plugin vim
Classifier: Development Status :: 4 - Beta
Classifier: Environment :: Plugins
Classifier: Intended Audience :: End Users/Desktop
Classifier: License :: OSI Approved :: GNU General Public License v3 (GPLv3)
Classifier: Operating System :: OS Independent
Classifier: Programming Language :: Python :: 3
Classifier: Programming Language :: Python :: 3.6
Classifier: Programming Language :: Python :: 3.7
Classifier: Programming Language :: Python :: 3.8
Classifier: Programming Language :: Python :: 3.9
Classifier: Programming Language :: Python :: 3.10
License-File: LICENSE
Requires-Dist: plover >=4.0.0.dev8
Requires-Dist: plover-python-dictionary-lib ~=0.4
Requires-Dist: plover-clr-trans-state
Requires-Dist: num2words
